similari_trackers_rs-0.26.12.dist-info/METADATA
similari_trackers_rs-0.26.12.dist-info/WHEEL
similari_trackers_rs-0.26.12.dist-info/license_files/LICENSE
similari/__init__.py
similari/similari.cpython-312-aarch64-linux-gnu.so
similari_trackers_rs-0.26.12.dist-info/RECORD
