Metadata-Version: 2.4
Name: similari-trackers-rs
Version: 0.26.12
Classifier: Programming Language :: Rust
Classifier: Programming Language :: Python :: Implementation :: CPython
Classifier: Programming Language :: Python :: Implementation :: PyPy
License-File: LICENSE
Summary: Machine learning framework for building object trackers and similarity search engines
Keywords: machine-learning,similarity,tracking,SORT,DeepSORT
Home-Page: https://github.com/insight-platform/Similari
Author: Ivan Kudriavtsev <ivan.a.kudryavtsev@gmail.com>
Author-email: Ivan Kudriavtsev <ivan.a.kudryavtsev@gmail.com>
License: Apache-2.0
Requires-Python: >=3.8
Project-URL: Source Code, https://github.com/insight-platform/Similari
